ThreatHunter/MDART.py~
ThreatHunter/MDART.py~~
ThreatHunter/THmain.py
ThreatHunter/THmain.py~
ThreatHunter/YARA.py
ThreatHunter/YARA.py~
ThreatHunter/__init__.py
ThreatHunter/__init__.py~
ThreatHunter/apk.py
ThreatHunter/cap.py
ThreatHunter/cap.py~
ThreatHunter/date__time.py
ThreatHunter/draft.py
ThreatHunter/elf.py
ThreatHunter/mach_O.py
ThreatHunter/mytimer.py
ThreatHunter/overwrite.py
ThreatHunter/pe.py
ThreatHunter/r2.py
ThreatHunter/show_progress.py
ThreatHunter/test.py
ThreatHunter/__pycache__/MDART.cpython-311.pyc
ThreatHunter/__pycache__/YARA.cpython-311.pyc
ThreatHunter/__pycache__/__init__.cpython-311.pyc
ThreatHunter/__pycache__/cap.cpython-311.pyc
ThreatHunter/__pycache__/date__time.cpython-311.pyc
ThreatHunter/__pycache__/elf.cpython-311.pyc
ThreatHunter/__pycache__/mytimer.cpython-311.pyc
ThreatHunter/__pycache__/overwrite.cpython-311.pyc
ThreatHunter/__pycache__/pe.cpython-311.pyc
ThreatHunter/__pycache__/show_progress.cpython-311.pyc
ThreatHunter/miscelenoue_rule/Adobe_Type_1_Font.yar.zip
ThreatHunter/miscelenoue_rule/Adobe_XMP_Identifier.yar
ThreatHunter/rules/pe_file_pyinstaller.yara
ThreatHunter/rules/APT/Confucius_B.yar
ThreatHunter/rules/APT/Cotx_RAT.yar
ThreatHunter/rules/APT/RoyalRoad_RTF.yar
ThreatHunter/rules/awesome_yara/Adobe_Flash_DRM_Use_After_Free.rule
ThreatHunter/rules/awesome_yara/AgentTesla.rule
ThreatHunter/rules/awesome_yara/Apt29_DLL_May2022.yar
ThreatHunter/rules/awesome_yara/Base64_Encoded_Powershell_Directives.rule
ThreatHunter/rules/awesome_yara/Base64_Encoded_Powershell_Directives.yar
ThreatHunter/rules/awesome_yara/Base64_Encoded_URL.yar
ThreatHunter/rules/awesome_yara/CVE_2014_1761.yar
ThreatHunter/rules/awesome_yara/CVE_2018_4878_0day_ITW.rule
ThreatHunter/rules/awesome_yara/ClamAV_Emotet_String_Aggregrate.rule
ThreatHunter/rules/awesome_yara/Controlword_Whitespace_RTF.yar
ThreatHunter/rules/awesome_yara/EPPlus_OOXML_Document.yar
ThreatHunter/rules/awesome_yara/Embedded_PE.rule
ThreatHunter-1.1.4.dist-info/LICENSE
ThreatHunter-1.1.4.dist-info/METADATA
ThreatHunter-1.1.4.dist-info/WHEEL
ThreatHunter-1.1.4.dist-info/entry_points.txt
ThreatHunter-1.1.4.dist-info/top_level.txt
ThreatHunter-1.1.4.dist-info/RECORD
