Metadata-Version: 2.1
Name: ThreatHunter
Version: 1.1.4
Author: Wambua aka Bullet Angel
License: MIT
Keywords: MalwareDART,ThreatHunter,malware,malware-analysis,malware-scan,malware-detection,trojan,virus
Classifier: Environment :: Console
Classifier: Operating System :: OS Independent
Classifier: Natural Language :: English
Classifier: Operating System :: OS Independent
Classifier: Programming Language :: Python
Classifier: Programming Language :: Python :: 3 :: Only
Classifier: Programming Language :: Python :: 3
Classifier: Programming Language :: Python :: 3.7
Classifier: Programming Language :: Python :: 3.8
Classifier: Programming Language :: Python :: 3.9
Classifier: Programming Language :: Python :: 3.10
Classifier: Programming Language :: Python :: 3.11
Requires-Python: >=3
License-File: LICENSE
Requires-Dist: argparse
Requires-Dist: capstone
Requires-Dist: pefile
Requires-Dist: progressbar
Requires-Dist: pyelftools
Requires-Dist: pymem
Requires-Dist: r2pipe
Requires-Dist: yara-python
